setup.py
dav_probdist/Binomialdistribution.py
dav_probdist/Gaussiandistribution.py
dav_probdist/Generaldistribution.py
dav_probdist/__init__.py
dav_probdist.egg-info/PKG-INFO
dav_probdist.egg-info/SOURCES.txt
dav_probdist.egg-info/dependency_links.txt
dav_probdist.egg-info/not-zip-safe
dav_probdist.egg-info/top_level.txt