Metadata-Version: 1.0
Name: dav-probdist
Version: 0.1
Summary: Gaussian and Binomial distributions
Home-page: UNKNOWN
Author: David Hazarika
Author-email: UNKNOWN
License: UNKNOWN
Platform: UNKNOWN
